{"dataset": "a9b80e8f-b8e5-4b3a-99b1-95f273956ad3", "code": "voldoende-informatie-door-gemeente-detail", "creator": "Burgerbevraging Gemeente-Stadsmonitor, Agentschap Binnenlands Bestuur", "name": "Voldoende informatie door gemeente (detail)", "description": "Aandeel van de inwoners dat zich voldoende ge\u00efnformeerd voelt over de activiteiten, de ingrepen en plannen, de beslissingen en de voorzieningen in en door de gemeente/stad.", "url": "https://gemeente-stadsmonitor.vlaanderen.be/over-de-monitor/overzicht-indicatoren/voldoende-informatie-door-gemeente-detail", "unit": "procent personen", "firstDate": "2008-01-01 00:00:00.000000 +00:00", "lastDate": "2023-01-01 00:00:00.000000 +00:00"}