{"dataset": "69153887-1a94-4a41-a13e-6be38bdc176c", "code": "deelname-aan-buurtactiviteiten", "creator": "Burgerbevraging Gemeente-Stadsmonitor, Agentschap Binnenlands Bestuur", "name": "Deelname aan buurtactiviteiten", "description": "Aandeel van de inwoners dat het afgelopen jaar heeft deelgenomen aan een buurtactiviteit.", "url": "https://gemeente-stadsmonitor.vlaanderen.be/over-de-monitor/overzicht-indicatoren/deelname-aan-buurtactiviteiten", "unit": "procent personen", "firstDate": "2011-01-01 00:00:00.000000 +00:00", "lastDate": "2023-01-01 00:00:00.000000 +00:00"}