{"dataset": "533b03e1-4218-4949-be37-23dd03e69815", "code": "buurthinder-milieuhinder", "creator": "Burgerbevraging Gemeente-Stadsmonitor, Agentschap Binnenlands Bestuur", "name": "Buurthinder: milieuhinder", "description": "Aandeel van de inwoners dat de afgelopen maand hinder heeft ondervonden van zwerfvuil, dieren of hondenpoep.", "url": "https://gemeente-stadsmonitor.vlaanderen.be/over-de-monitor/overzicht-indicatoren/buurthinder-milieuhinder", "unit": "procent personen", "firstDate": "2011-01-01 00:00:00.000000 +00:00", "lastDate": "2023-01-01 00:00:00.000000 +00:00"}