{"dataset": "b42a9f8f-4066-439a-9eb7-4afa4d664c82", "code": "meerderjarige-nieuwkomers", "creator": "Agentschap Binnenlands Bestuur, Kruispuntbank Inburgering", "name": "Meerderjarige nieuwkomers", "description": "Aantal meerderjarige nieuwkomers. Nieuwkomers zijn personen die zich recentelijk, voor het eerst en voor langere duur in Vlaanderen komen vestigen. Personen die hier slechts tijdelijk verblijven, worden niet als nieuwkomers beschouwd. Concreet gaat het om de som van:- het aantal meerderjarige inburgeraars met een vreemde (=niet-Belgische) nationaliteit dat zich voor het eerst en voor langere duur (meer dan 3 maanden) in Belgi\u00eb komt vestigen;- het aantal meerderjarige inburgeraars met de Belgische nationaliteit dat voor het eerst sedert niet langer dan 12 opeenvolgende maanden in het bevolkingsregister van de gemeente werd ingeschreven;- het aantal meerderjarige asielzoekers dat meer dan 4 maanden geleden een asielaanvraag heeft ingediend;- het aantal meerderjarige personen dat recent als doelgroep van inburgering werd gedetecteerd, maar niet onder categorie 1, 2 en 3 valt (bv. slachtoffers van mensenhandel met een attest van immatriculatie model A) dat geldig is voor 3 maanden.", "url": "https://gemeente-stadsmonitor.vlaanderen.be/over-de-monitor/overzicht-indicatoren/meerderjarige-nieuwkomers", "unit": "per 1.000 inwoners nieuwkomers", "firstDate": "2008-01-01 00:00:00.000000 +00:00", "lastDate": "2021-01-01 00:00:00.000000 +00:00"}