{"dataset": "2f97e1d6-9d6c-47d2-84a7-6bdcfdc40bca", "code": "geboorten", "creator": "Statbel", "name": "Geboorten", "description": "Het aantal levendgeborenen bij vrouwen uit de wettelijke bevolking met een offici\u00eble woonplaats (hoofdverblijfplaats) in het Vlaamse Gewest.", "url": "https://gemeente-stadsmonitor.vlaanderen.be/over-de-monitor/overzicht-indicatoren/geboorten", "unit": "per 1.000 inwoners levendgeborenen", "firstDate": "1997-01-01 00:00:00.000000 +00:00", "lastDate": "2022-01-01 00:00:00.000000 +00:00"}