{"dataset": "090cd424-73de-4eb0-9977-dfeaaa44a507", "code": "residentiele-ouderenzorg", "creator": "Vlaams Agentschap Zorg en Gezondheid", "name": "Residenti\u00eble ouderenzorg", "description": "Het aantal plaatsen in de residenti\u00eble ouderenzorg bestaat uit het aantal plaatsen in de woonzorgcentra en het aantal plaatsen in de assistentiewoningen. Beide zijn voorzieningen die gebruikers vanaf 65 jaar permanente huisvesting en gehele of gedeeltelijke zorgondersteuning bieden. Het gaat in beide soorten voorzieningen om de erkende plaatsen en de plaatsen waarvoor erkenning in onderzoek is. Er wordt geen onderscheid gemaakt tussen openbare of private voorzieningen.", "url": "https://gemeente-stadsmonitor.vlaanderen.be/over-de-monitor/overzicht-indicatoren/residentiele-ouderenzorg", "unit": "per 100 inwoners plaatsen", "firstDate": "1998-01-01 00:00:00.000000 +00:00", "lastDate": "2023-01-01 00:00:00.000000 +00:00"}